frontend_kit/__init__.py
frontend_kit/apps.py
frontend_kit/manifest.py
frontend_kit/page.py
frontend_kit/py.typed
frontend_kit/utils.py
frontend_kit/management/__init__.py
frontend_kit/management/commands/__init__.py
frontend_kit/management/commands/scaffold.py
frontend_kit/scaffold/vite.config.js
frontend_kit/scaffold/frontend/layouts/base/__init__.py
frontend_kit/scaffold/frontend/layouts/base/entry.head.ts
frontend_kit/scaffold/frontend/layouts/base/entry.ts
frontend_kit/scaffold/frontend/layouts/base/index.html
frontend_kit/scaffold/frontend/layouts/base/main.css
frontend_kit/scaffold/frontend/pages/home/__init__.py
frontend_kit/scaffold/frontend/pages/home/entry.ts
frontend_kit/scaffold/frontend/pages/home/index.html
frontend_kit/templatetags/__init__.py
frontend_kit/templatetags/fk_tags.py
django_frontend_kit-0.5.0.dist-info/METADATA
django_frontend_kit-0.5.0.dist-info/WHEEL
django_frontend_kit-0.5.0.dist-info/licenses/LICENSE
django_frontend_kit-0.5.0.dist-info/RECORD
