Metadata-Version: 2.4
Name: django-frontend-kit
Version: 0.5.0
Summary: Opinionated Django frontend scaffolder using ViteJS
Project-URL: Repository, https://github.com/devwaseem/django-frontend-kit
Author-email: Waseem Akram <waseem07799@gmail.com>
License-Expression: MIT
License-File: LICENSE
Keywords: django,django-frontend-kit,django-vitejs,vitejs
Classifier: Development Status :: 4 - Beta
Classifier: Framework :: Django :: 3.0
Classifier: Framework :: Django :: 4
Classifier: Framework :: Django :: 4.0
Classifier: Framework :: Django :: 4.1
Classifier: Framework :: Django :: 4.2
Classifier: Framework :: Django :: 5.0
Classifier: Framework :: Django :: 5.1
Classifier: License :: OSI Approved :: MIT License
Requires-Python: >=3.9
Requires-Dist: django-render-block>=0.10
Requires-Dist: django>=4.2
